edl/__init__.py
edl/__version__.py
edl_reader-0.1.14.dist-info/LICENSE
edl_reader-0.1.14.dist-info/METADATA
edl_reader-0.1.14.dist-info/WHEEL
edl_reader-0.1.14.dist-info/top_level.txt
edl_reader-0.1.14.dist-info/RECORD
