Metadata-Version: 2.1
Name: edl-reader
Version: 0.1.14
Summary: Simple EDL reading library.
Home-page: http://www.simon-hargreaves.com/python-edl
Author: Simon Hargreaves,
Author-email: simon@simon-hargreaves.com,
Maintainer: CG Wire,
Maintainer-email: evan@cg-wire.com,
License: MIT
Keywords: cg,production,edl,edit,decision,list,parser
Classifier: Development Status :: 3 - Alpha
Classifier: Environment :: Console
Classifier: Intended Audience :: Developers
Classifier: License :: OSI Approved :: MIT License
Classifier: Operating System :: MacOS :: MacOS X
Classifier: Operating System :: Microsoft :: Windows
Classifier: Operating System :: POSIX
Classifier: Programming Language :: Python
Classifier: Natural Language :: English
Classifier: Topic :: Multimedia :: Video
Classifier: Topic :: Software Development :: Libraries
Classifier: Programming Language :: Python :: 3.7
Classifier: Programming Language :: Python :: 3.8
Classifier: Programming Language :: Python :: 3.9
Classifier: Programming Language :: Python :: 3.10
Classifier: Programming Language :: Python :: 3.11
Classifier: Programming Language :: Python :: Implementation :: CPython
Classifier: Programming Language :: Python :: Implementation :: PyPy
Classifier: Topic :: Multimedia :: Graphics
Requires-Python: >= 3.7
License-File: LICENSE
Requires-Dist: timecode (>=1.3.1)
Provides-Extra: dev
Requires-Dist: wheel ; extra == 'dev'
Provides-Extra: lint
Requires-Dist: black (==23.3.0) ; extra == 'lint'
Requires-Dist: pre-commit (==3.2.2) ; extra == 'lint'
Provides-Extra: test
Requires-Dist: pytest ; extra == 'test'
Requires-Dist: pytest-cov ; extra == 'test'
